[
  { "id": "dongwon", "name": "동원", "logo": "brand-dongwon.svg" },
  { "id": "daesang", "name": "대상", "logo": "brand-daesang.svg" },
  { "id": "sajo", "name": "사조", "logo": "brand-sajo.svg" },
  { "id": "pullmuone", "name": "풀무원", "logo": "brand-pullmuone.svg" },
  { "id": "samyang", "name": "삼양", "logo": "brand-samyang.svg" },
  { "id": "gompyo", "name": "곰표", "logo": "brand-gompyo.svg" },
  { "id": "cj", "name": "제일제당", "logo": "brand-cj.svg" },
  { "id": "qone", "name": "큐원", "logo": "brand-qone.svg" },
  { "id": "paldo", "name": "팔도", "logo": "brand-paldo.svg" },
  { "id": "ottogi", "name": "오뚜기", "logo": "brand-ottogi.svg" },
  { "id": "ourhome", "name": "아워홈", "logo": "brand-ourhome.svg" },
  { "id": "orion", "name": "오리온", "logo": "brand-orion.svg" },
  { "id": "nomgshim", "name": "농심", "logo": "brand-nomgshim.svg" },
  { "id": "lottewell", "name": "롯데웰푸드", "logo": "brand-lottewell.svg" },
  { "id": "crown", "name": "크라운", "logo": "brand-crown.svg" },
  { "id": "haetai", "name": "해태", "logo": "brand-haetai.svg" },
  { "id": "maxim", "name": "동서식품", "logo": "brand-maxim.svg" },
  { "id": "mombext", "name": "몽베스트", "logo": "brand-mombext.svg" },
  { "id": "maeil", "name": "매일유업", "logo": "brand-maeil.svg" },
  { "id": "pigeon", "name": "피죤", "logo": "brand-pigeon.svg" },
  { "id": "ackeyoun", "name": "애경", "logo": "brand-ackeyoun.svg" },
  { "id": "lion", "name": "라이언", "logo": "brand-lion.svg" },
  { "id": "lglife", "name": "엘지생활건강", "logo": "brand-lglife.svg" },
  { "id": "yuhan", "name": "유한킴벌리", "logo": "brand-yuhan.svg" },
  { "id": "hollys", "name": "할리스", "logo": "brand-hollys.svg" },
  { "id": "haggen", "name": "하겐다즈", "logo": "brand-haggen.svg" },
  { "id": "mcnuls", "name": "맥널티", "logo": "brand-mcnuls.svg" }
]
